avro_to_python_etp/__init__.py
avro_to_python_etp/avpr_to_avsc.py
avro_to_python_etp/classes/__init__.py
avro_to_python_etp/classes/field.py
avro_to_python_etp/classes/file.py
avro_to_python_etp/classes/node.py
avro_to_python_etp/classes/reference.py
avro_to_python_etp/cli.py
avro_to_python_etp/raw_files/tests/test_arrays.py
avro_to_python_etp/reader/__init__.py
avro_to_python_etp/reader/read.py
avro_to_python_etp/templates/baseTemplate.j2
avro_to_python_etp/templates/fields/arrayField.j2
avro_to_python_etp/templates/fields/fieldFactory.j2
avro_to_python_etp/templates/fields/mapField.j2
avro_to_python_etp/templates/fields/primitiveField.j2
avro_to_python_etp/templates/fields/referenceField.j2
avro_to_python_etp/templates/fields/unionField.j2
avro_to_python_etp/templates/files/enum.j2
avro_to_python_etp/templates/files/fixed.j2
avro_to_python_etp/templates/files/helpers.j2
avro_to_python_etp/templates/files/init.j2
avro_to_python_etp/templates/files/manifest.j2
avro_to_python_etp/templates/files/pip_init.j2
avro_to_python_etp/templates/files/py.j2
avro_to_python_etp/templates/files/pyproject.j2
avro_to_python_etp/templates/files/record.j2
avro_to_python_etp/templates/files/setup.j2
avro_to_python_etp/templates/imports/basicImports.j2
avro_to_python_etp/templates/imports/fileImports.j2
avro_to_python_etp/templates/macro.j2
avro_to_python_etp/templates/partials/avroSchema.j2
avro_to_python_etp/templates/partials/footer.j2
avro_to_python_etp/templates/partials/header.j2
avro_to_python_etp/templates/partials/meta.j2
avro_to_python_etp/templates/partials/objectSetter.j2
avro_to_python_etp/utils/__init__.py
avro_to_python_etp/utils/avro/__init__.py
avro_to_python_etp/utils/avro/files/__init__.py
avro_to_python_etp/utils/avro/files/enum.py
avro_to_python_etp/utils/avro/files/fixed.py
avro_to_python_etp/utils/avro/files/meta.py
avro_to_python_etp/utils/avro/files/record.py
avro_to_python_etp/utils/avro/helpers.py
avro_to_python_etp/utils/avro/primitive_types.py
avro_to_python_etp-1.0.11.dist-info/AUTHORS.rst
avro_to_python_etp-1.0.11.dist-info/LICENSE
avro_to_python_etp-1.0.11.dist-info/METADATA
avro_to_python_etp-1.0.11.dist-info/WHEEL
avro_to_python_etp-1.0.11.dist-info/entry_points.txt
avro_to_python_etp-1.0.11.dist-info/RECORD
