Metadata-Version: 2.3
Name: avro-to-python-etp
Version: 1.0.11
Summary: Light tool for compiling avro schema files (.avsc) to python classes making using avro schemata easy.
License: MIT
Keywords: avro,etp
Author: Scott Rothbarth
Author-email: srserves85@gmail.com
Requires-Python: >=3.9, <4.0.0
Classifier: Programming Language :: Python :: 3
Classifier: License :: OSI Approved :: MIT License
Classifier: Operating System :: OS Independent
Requires-Dist: Jinja2
Requires-Dist: anytree
Requires-Dist: avro
Requires-Dist: click
Requires-Dist: nested-lookup
Requires-Dist: setuptools (>=77.0.3,<78.0.0)
Requires-Dist: typingx
Requires-Dist: wheel
